{
"type": "FeatureCollection",
"crs": { "type": "name", "properties": { "name": "urn:ogc:def:crs:OGC:1.3:CRS84" } },
"features": [
{ "type": "Feature", "properties": { "city": "bengaluru", "AQI": 5.0, "latitude": 12.9767936, "longitude": 77.590082 }, "geometry": { "type": "Point", "coordinates": [ 77.590082, 12.9767936 ] } },
{ "type": "Feature", "properties": { "city": "delhi", "AQI": 5.0, "latitude": 28.6517178, "longitude": 77.2219388 }, "geometry": { "type": "Point", "coordinates": [ 77.2219388, 28.6517178 ] } },
{ "type": "Feature", "properties": { "city": "lucknow", "AQI": 4.0, "latitude": 26.8381, "longitude": 80.9346001 }, "geometry": { "type": "Point", "coordinates": [ 80.9346001, 26.8381 ] } },
{ "type": "Feature", "properties": { "city": "chennai", "AQI": 3.0, "latitude": 13.0836939, "longitude": 80.270186 }, "geometry": { "type": "Point", "coordinates": [ 80.270186, 13.0836939 ] } }
]
}
